{
  "serialNumberInserv" : "1458215",
  "system" : {
    "companyName" : "Hangman",
    "model" : "7200",
    "fullModel" : "HPE_3PAR 7200",
    "osVersion" : "3.3.1.410 (MU2)",
    "patches" : [ "P30" ],
    "sp" : {
      "spId" : "5791832",
      "spModel" : "VMware Virtual Platform",
      "spVersion" : "5.0.3.0-24806"
    },
    "productSKU" : "QR482A",
    "productFamily" : "7000",
    "recommended" : {
      "conditionalPatches" : [ "P32" ]
    },
    "portsHWInfo" : [ {
      "nsp" : "0:2:4",
      "brand" : "EMULEX",
      "model" : "LPe12004",
      "rev" : "03",
      "firmware" : "2.10.X.3",
      "serial" : "5CF446065T"
    }, {
      "nsp" : "0:0:1",
      "brand" : "LSI",
      "model" : "9205-8e",
      "rev" : "01",
      "firmware" : "17.11.03.00",
      "serial" : "Onboard"
    }, {
      "nsp" : "0:1:1",
      "brand" : "EMULEX",
      "model" : "LPe12002",
      "rev" : "03",
      "firmware" : "2.10.X.3",
      "serial" : "Onboard"
    }, {
      "nsp" : "1:2:4",
      "brand" : "EMULEX",
      "model" : "LPe12004",
      "rev" : "03",
      "firmware" : "2.10.X.3",
      "serial" : "5CF446065G"
    }, {
      "nsp" : "0:0:2",
      "brand" : "LSI",
      "model" : "9205-8e",
      "rev" : "01",
      "firmware" : "17.11.03.00",
      "serial" : "Onboard"
    }, {
      "nsp" : "0:1:2",
      "brand" : "EMULEX",
      "model" : "LPe12002",
      "rev" : "03",
      "firmware" : "2.10.X.3",
      "serial" : "Onboard"
    }, {
      "nsp" : "0:2:2",
      "brand" : "EMULEX",
      "model" : "LPe12004",
      "rev" : "03",
      "firmware" : "2.10.X.3",
      "serial" : "5CF446065T"
    }, {
      "nsp" : "1:2:3",
      "brand" : "EMULEX",
      "model" : "LPe12004",
      "rev" : "03",
      "firmware" : "2.10.X.3",
      "serial" : "5CF446065G"
    }, {
      "nsp" : "1:1:1",
      "brand" : "EMULEX",
      "model" : "LPe12002",
      "rev" : "03",
      "firmware" : "2.10.X.3",
      "serial" : "Onboard"
    }, {
      "nsp" : "1:0:1",
      "brand" : "LSI",
      "model" : "9205-8e",
      "rev" : "01",
      "firmware" : "17.11.03.00",
      "serial" : "Onboard"
    }, {
      "nsp" : "1:2:1",
      "brand" : "EMULEX",
      "model" : "LPe12004",
      "rev" : "03",
      "firmware" : "2.10.X.3",
      "serial" : "5CF446065G"
    }, {
      "nsp" : "1:1:2",
      "brand" : "EMULEX",
      "model" : "LPe12002",
      "rev" : "03",
      "firmware" : "2.10.X.3",
      "serial" : "Onboard"
    }, {
      "nsp" : "1:2:2",
      "brand" : "EMULEX",
      "model" : "LPe12004",
      "rev" : "03",
      "firmware" : "2.10.X.3",
      "serial" : "5CF446065G"
    }, {
      "nsp" : "0:2:1",
      "brand" : "EMULEX",
      "model" : "LPe12004",
      "rev" : "03",
      "firmware" : "2.10.X.3",
      "serial" : "5CF446065T"
    }, {
      "nsp" : "1:3:1",
      "brand" : "Intel",
      "model" : "e1000e",
      "firmware" : "3.2.6-k",
      "serial" : "Onboard"
    }, {
      "nsp" : "1:0:2",
      "brand" : "LSI",
      "model" : "9205-8e",
      "rev" : "01",
      "firmware" : "17.11.03.00",
      "serial" : "Onboard"
    }, {
      "nsp" : "0:2:3",
      "brand" : "EMULEX",
      "model" : "LPe12004",
      "rev" : "03",
      "firmware" : "2.10.X.3",
      "serial" : "5CF446065T"
    }, {
      "nsp" : "0:3:1",
      "brand" : "Intel",
      "model" : "e1000e",
      "firmware" : "3.2.6-k",
      "serial" : "Onboard"
    } ]
  },
  "capacity" : {
    "total" : {
      "virtualSizeTiB" : 270.771484375,
      "sizeTiB" : 462.84375,
      "freeTiB" : 127.3447265625,
      "freePct" : 27.513545989990234,
      "freePctZeroPredictedDate" : "2019-06-15T03:37:55Z",
      "allocatedCapacityTiB" : 335.498046875,
      "failedCapacityTiB" : 0.0009765625,
      "systemAllocatedTiB" : 20.6572265625,
      "volumesAllocatedTiB" : 314.8359375,
      "otherAllocatedTiB" : 0.0048828125,
      "volumesVirtualSizeTiB" : 270.771484375,
      "usedSpaceTiB" : 274.400390625,
      "compactionRatio" : 1,
      "overprovisioningRatio" : 0.7099999785423279
    },
    "byType" : {
      "fc" : {
        "sizeTiB" : 6.3984375,
        "freeTiB" : 5.3544921875,
        "freePct" : 83.68437194824219,
        "usedBalancedPct" : 100,
        "sizeBalancedPct" : 100
      },
      "nl" : {
        "sizeTiB" : 423.1640625,
        "freeTiB" : 99.5888671875,
        "freePct" : 23.534339904785156,
        "freePctZeroPredictedDate" : "2019-04-15T03:37:55Z",
        "usedBalancedPct" : 100,
        "sizeBalancedPct" : 100
      },
      "ssd" : {
        "sizeTiB" : 33.28125,
        "freeTiB" : 22.40625,
        "freePct" : 67.32394409179688,
        "usedBalancedPct" : 100,
        "sizeBalancedPct" : 100
      }
    },
    "arrayType" : "MixedArray"
  },
  "performance" : {
    "portBandwidthData" : {
      "total" : {
        "dataRateKBPSAvg" : 278291,
        "dataRateKBPSMax" : 492521,
        "dataRateKBPSMin" : 14728,
        "iopsAvg" : 10118,
        "iopsMax" : 18462,
        "iopsMin" : 520,
        "ioSizeAvg" : 31.479961395263672,
        "ioSizeMax" : 60,
        "ioSizeMin" : 0,
        "queueLengthAvg" : 5,
        "queueLengthMax" : 78.5,
        "queueLengthMin" : 0,
        "serviceTimeMSAvg" : 1.699960470199585,
        "serviceTimeMSMax" : 3,
        "serviceTimeMSMin" : 0
      },
      "read" : {
        "dataRateKBPSAvg" : 132658,
        "dataRateKBPSMax" : 357561,
        "dataRateKBPSMin" : 13332,
        "iopsAvg" : 6306,
        "iopsMax" : 14743,
        "iopsMin" : 476,
        "ioSizeAvg" : 20.919984817504883,
        "ioSizeMax" : 28,
        "ioSizeMin" : 0,
        "queueLengthAvg" : 0,
        "queueLengthMax" : 0,
        "queueLengthMin" : 0,
        "serviceTimeMSAvg" : 1.000063419342041,
        "serviceTimeMSMax" : 2,
        "serviceTimeMSMin" : 0
      },
      "write" : {
        "dataRateKBPSAvg" : 145633,
        "dataRateKBPSMax" : 441567,
        "dataRateKBPSMin" : 1395,
        "iopsAvg" : 3812,
        "iopsMax" : 11029,
        "iopsMin" : 44,
        "ioSizeAvg" : 50.88994598388672,
        "ioSizeMax" : 138,
        "ioSizeMin" : 0,
        "queueLengthAvg" : 0,
        "queueLengthMax" : 0,
        "queueLengthMin" : 0,
        "serviceTimeMSAvg" : 2.939973831176758,
        "serviceTimeMSMax" : 4,
        "serviceTimeMSMin" : 0
      }
    },
    "summary" : {
      "portInfo" : {
        "readServiceTimeColMillis" : 1.000063419342041,
        "writeServiceTimeColMillis" : 2.939973831176758,
        "totalServiceTimeColMillis" : 1.699960470199585
      }
    }
  },
  "disks" : {
    "total" : {
      "diskCount" : 168,
      "diskCountNormal" : 168
    },
    "byType" : {
      "fc" : {
        "diskCount" : 8,
        "diskCountBalancedPct" : 100,
        "diskCountNormal" : 8,
        "state" : "normal"
      },
      "nl" : {
        "diskCount" : 120,
        "diskCountBalancedPct" : 100,
        "diskCountNormal" : 120,
        "state" : "normal"
      },
      "ssd" : {
        "diskCount" : 40,
        "diskCountBalancedPct" : 100,
        "diskCountNormal" : 40,
        "state" : "normal"
      }
    },
    "state" : "normal"
  },
  "nodes" : {
    "nodeCount" : 2,
    "nodeCountOffline" : 0,
    "nodeCountMissing" : 0,
    "nodeTimeSkewSecs" : 0,
    "cageCount" : 8,
    "cpuAvgMax" : 29,
    "cpuMedianMax" : 13
  },
  "updated" : "2018-09-09T11:38:09Z",
  "authorized" : {
    "tenants" : [ "hpe" ]
  },
  "date" : "2018-09-09T11:38:09Z"
}