{
  "serialNumberInserv" : "6719395",
  "system" : {
    "companyName" : "Stuntmaster",
    "model" : "V800",
    "fullModel" : "InServ V800",
    "osVersion" : "3.3.1.261 (MU1)",
    "patches" : [ ],
    "sp" : {
      "spId" : "7792212",
      "spModel" : "PDSML",
      "spVersion" : "4.4.0.GA-58"
    },
    "productSKU" : "QR637A",
    "productFamily" : "10000",
    "portsHWInfo" : [ {
      "nsp" : "0:9:1",
      "brand" : "Intel",
      "model" : "e1000e",
      "firmware" : "3.2.6-k",
      "serial" : "Onboard"
    }, {
      "nsp" : "5:2:3",
      "brand" : "EMULEX",
      "model" : "LPe12004",
      "rev" : "03",
      "firmware" : "2.10.X.3",
      "serial" : "5CF20502GX"
    }, {
      "nsp" : "4:6:3",
      "brand" : "EMULEX",
      "model" : "LPe12004",
      "rev" : "03",
      "firmware" : "2.10.X.3",
      "serial" : "5CF1460272"
    }, {
      "nsp" : "4:0:2",
      "brand" : "EMULEX",
      "model" : "LPe12004",
      "rev" : "03",
      "firmware" : "2.10.X.3",
      "serial" : "5CF2290343"
    }, {
      "nsp" : "0:2:4",
      "brand" : "EMULEX",
      "model" : "LPe12004",
      "rev" : "03",
      "firmware" : "2.10.X.3",
      "serial" : "THC1244KGN"
    }, {
      "nsp" : "1:6:3",
      "brand" : "EMULEX",
      "model" : "LPe12004",
      "rev" : "03",
      "firmware" : "2.10.X.3",
      "serial" : "THT35275MN"
    }, {
      "nsp" : "0:0:1",
      "brand" : "EMULEX",
      "model" : "LPe12004",
      "rev" : "03",
      "firmware" : "2.10.X.3",
      "serial" : "5CF15005C3"
    }, {
      "nsp" : "0:7:2",
      "brand" : "QLOGIC",
      "model" : "QLE8242",
      "rev" : "58",
      "firmware" : "4.15.27",
      "serial" : "PCGLT0AST2YD7R"
    }, {
      "nsp" : "4:2:1",
      "brand" : "EMULEX",
      "model" : "LPe12004",
      "rev" : "03",
      "firmware" : "2.10.X.3",
      "serial" : "THC1294WPY"
    }, {
      "nsp" : "0:1:1",
      "brand" : "EMULEX",
      "model" : "LPe12004",
      "rev" : "03",
      "firmware" : "2.10.X.3",
      "serial" : "5CF14703WB"
    }, {
      "nsp" : "0:6:1",
      "brand" : "EMULEX",
      "model" : "LPe12004",
      "rev" : "03",
      "firmware" : "2.10.X.3",
      "serial" : "5CF14700VS"
    }, {
      "nsp" : "4:4:4",
      "brand" : "EMULEX",
      "model" : "LPe12004",
      "rev" : "03",
      "firmware" : "2.10.X.3",
      "serial" : "5CF231012P"
    }, {
      "nsp" : "5:9:1",
      "brand" : "Intel",
      "model" : "e1000e",
      "firmware" : "3.2.6-k",
      "serial" : "Onboard"
    }, {
      "nsp" : "4:1:1",
      "brand" : "EMULEX",
      "model" : "LPe12004",
      "rev" : "03",
      "firmware" : "2.10.X.3",
      "serial" : "5CF2300036"
    }, {
      "nsp" : "4:4:3",
      "brand" : "EMULEX",
      "model" : "LPe12004",
      "rev" : "03",
      "firmware" : "2.10.X.3",
      "serial" : "5CF231012P"
    }, {
      "nsp" : "0:1:4",
      "brand" : "EMULEX",
      "model" : "LPe12004",
      "rev" : "03",
      "firmware" : "2.10.X.3",
      "serial" : "5CF14703WB"
    }, {
      "nsp" : "4:5:1",
      "brand" : "EMULEX",
      "model" : "LPe12004",
      "rev" : "03",
      "firmware" : "2.10.X.3",
      "serial" : "5CF229030V"
    }, {
      "nsp" : "4:6:2",
      "brand" : "EMULEX",
      "model" : "LPe12004",
      "rev" : "03",
      "firmware" : "2.10.X.3",
      "serial" : "5CF1460272"
    }, {
      "nsp" : "4:2:2",
      "brand" : "EMULEX",
      "model" : "LPe12004",
      "rev" : "03",
      "firmware" : "2.10.X.3",
      "serial" : "THC1294WPY"
    }, {
      "nsp" : "0:4:2",
      "brand" : "EMULEX",
      "model" : "LPe12004",
      "rev" : "03",
      "firmware" : "2.10.X.3",
      "serial" : "THC1294TZR"
    }, {
      "nsp" : "1:2:4",
      "brand" : "EMULEX",
      "model" : "LPe12004",
      "rev" : "03",
      "firmware" : "2.10.X.3",
      "serial" : "THC13255FS"
    }, {
      "nsp" : "4:0:3",
      "brand" : "EMULEX",
      "model" : "LPe12004",
      "rev" : "03",
      "firmware" : "2.10.X.3",
      "serial" : "5CF2290343"
    }, {
      "nsp" : "1:6:2",
      "brand" : "EMULEX",
      "model" : "LPe12004",
      "rev" : "03",
      "firmware" : "2.10.X.3",
      "serial" : "THT35275MN"
    }, {
      "nsp" : "0:5:1",
      "brand" : "EMULEX",
      "model" : "LPe12004",
      "rev" : "03",
      "firmware" : "2.10.X.3",
      "serial" : "5CF231001Y"
    }, {
      "nsp" : "4:1:4",
      "brand" : "EMULEX",
      "model" : "LPe12004",
      "rev" : "03",
      "firmware" : "2.10.X.3",
      "serial" : "5CF2300036"
    }, {
      "nsp" : "5:6:4",
      "brand" : "EMULEX",
      "model" : "LPe12004",
      "rev" : "03",
      "firmware" : "2.10.X.3",
      "serial" : "THC12510SW"
    }, {
      "nsp" : "5:6:1",
      "brand" : "EMULEX",
      "model" : "LPe12004",
      "rev" : "03",
      "firmware" : "2.10.X.3",
      "serial" : "THC12510SW"
    }, {
      "nsp" : "0:0:2",
      "brand" : "EMULEX",
      "model" : "LPe12004",
      "rev" : "03",
      "firmware" : "2.10.X.3",
      "serial" : "5CF15005C3"
    }, {
      "nsp" : "5:2:4",
      "brand" : "EMULEX",
      "model" : "LPe12004",
      "rev" : "03",
      "firmware" : "2.10.X.3",
      "serial" : "5CF20502GX"
    }, {
      "nsp" : "0:1:2",
      "brand" : "EMULEX",
      "model" : "LPe12004",
      "rev" : "03",
      "firmware" : "2.10.X.3",
      "serial" : "5CF14703WB"
    }, {
      "nsp" : "0:2:2",
      "brand" : "EMULEX",
      "model" : "LPe12004",
      "rev" : "03",
      "firmware" : "2.10.X.3",
      "serial" : "THC1244KGN"
    }, {
      "nsp" : "1:2:3",
      "brand" : "EMULEX",
      "model" : "LPe12004",
      "rev" : "03",
      "firmware" : "2.10.X.3",
      "serial" : "THC13255FS"
    }, {
      "nsp" : "4:5:2",
      "brand" : "EMULEX",
      "model" : "LPe12004",
      "rev" : "03",
      "firmware" : "2.10.X.3",
      "serial" : "5CF229030V"
    }, {
      "nsp" : "4:7:1",
      "brand" : "QLOGIC",
      "model" : "QLE8242",
      "rev" : "58",
      "firmware" : "4.15.27",
      "serial" : "PCGLT0AST2FCW7"
    }, {
      "nsp" : "0:7:1",
      "brand" : "QLOGIC",
      "model" : "QLE8242",
      "rev" : "58",
      "firmware" : "4.15.27",
      "serial" : "PCGLT0AST2YD7R"
    }, {
      "nsp" : "0:6:4",
      "brand" : "EMULEX",
      "model" : "LPe12004",
      "rev" : "03",
      "firmware" : "2.10.X.3",
      "serial" : "5CF14700VS"
    }, {
      "nsp" : "0:4:3",
      "brand" : "EMULEX",
      "model" : "LPe12004",
      "rev" : "03",
      "firmware" : "2.10.X.3",
      "serial" : "THC1294TZR"
    }, {
      "nsp" : "4:4:2",
      "brand" : "EMULEX",
      "model" : "LPe12004",
      "rev" : "03",
      "firmware" : "2.10.X.3",
      "serial" : "5CF231012P"
    }, {
      "nsp" : "0:0:3",
      "brand" : "EMULEX",
      "model" : "LPe12004",
      "rev" : "03",
      "firmware" : "2.10.X.3",
      "serial" : "5CF15005C3"
    }, {
      "nsp" : "4:4:1",
      "brand" : "EMULEX",
      "model" : "LPe12004",
      "rev" : "03",
      "firmware" : "2.10.X.3",
      "serial" : "5CF231012P"
    }, {
      "nsp" : "4:2:4",
      "brand" : "EMULEX",
      "model" : "LPe12004",
      "rev" : "03",
      "firmware" : "2.10.X.3",
      "serial" : "THC1294WPY"
    }, {
      "nsp" : "0:1:3",
      "brand" : "EMULEX",
      "model" : "LPe12004",
      "rev" : "03",
      "firmware" : "2.10.X.3",
      "serial" : "5CF14703WB"
    }, {
      "nsp" : "0:5:2",
      "brand" : "EMULEX",
      "model" : "LPe12004",
      "rev" : "03",
      "firmware" : "2.10.X.3",
      "serial" : "5CF231001Y"
    }, {
      "nsp" : "1:2:1",
      "brand" : "EMULEX",
      "model" : "LPe12004",
      "rev" : "03",
      "firmware" : "2.10.X.3",
      "serial" : "THC13255FS"
    }, {
      "nsp" : "4:0:4",
      "brand" : "EMULEX",
      "model" : "LPe12004",
      "rev" : "03",
      "firmware" : "2.10.X.3",
      "serial" : "5CF2290343"
    }, {
      "nsp" : "4:7:2",
      "brand" : "QLOGIC",
      "model" : "QLE8242",
      "rev" : "58",
      "firmware" : "4.15.27",
      "serial" : "PCGLT0AST2FCW7"
    }, {
      "nsp" : "0:5:3",
      "brand" : "EMULEX",
      "model" : "LPe12004",
      "rev" : "03",
      "firmware" : "2.10.X.3",
      "serial" : "5CF231001Y"
    }, {
      "nsp" : "0:4:4",
      "brand" : "EMULEX",
      "model" : "LPe12004",
      "rev" : "03",
      "firmware" : "2.10.X.3",
      "serial" : "THC1294TZR"
    }, {
      "nsp" : "4:1:3",
      "brand" : "EMULEX",
      "model" : "LPe12004",
      "rev" : "03",
      "firmware" : "2.10.X.3",
      "serial" : "5CF2300036"
    }, {
      "nsp" : "5:6:3",
      "brand" : "EMULEX",
      "model" : "LPe12004",
      "rev" : "03",
      "firmware" : "2.10.X.3",
      "serial" : "THC12510SW"
    }, {
      "nsp" : "1:9:1",
      "brand" : "Intel",
      "model" : "e1000e",
      "firmware" : "3.2.6-k",
      "serial" : "Onboard"
    }, {
      "nsp" : "1:2:2",
      "brand" : "EMULEX",
      "model" : "LPe12004",
      "rev" : "03",
      "firmware" : "2.10.X.3",
      "serial" : "THC13255FS"
    }, {
      "nsp" : "0:6:3",
      "brand" : "EMULEX",
      "model" : "LPe12004",
      "rev" : "03",
      "firmware" : "2.10.X.3",
      "serial" : "5CF14700VS"
    }, {
      "nsp" : "4:5:3",
      "brand" : "EMULEX",
      "model" : "LPe12004",
      "rev" : "03",
      "firmware" : "2.10.X.3",
      "serial" : "5CF229030V"
    }, {
      "nsp" : "1:7:2",
      "brand" : "QLOGIC",
      "model" : "QLE8242",
      "rev" : "58",
      "firmware" : "4.15.27",
      "serial" : "PCGLT0AST2VE47"
    }, {
      "nsp" : "0:2:1",
      "brand" : "EMULEX",
      "model" : "LPe12004",
      "rev" : "03",
      "firmware" : "2.10.X.3",
      "serial" : "THC1244KGN"
    }, {
      "nsp" : "4:9:1",
      "brand" : "Intel",
      "model" : "e1000e",
      "firmware" : "3.2.6-k",
      "serial" : "Onboard"
    }, {
      "nsp" : "5:7:1",
      "brand" : "QLOGIC",
      "model" : "QLE8242",
      "rev" : "58",
      "firmware" : "4.15.27",
      "serial" : "PCGLT0AST2JD2U"
    }, {
      "nsp" : "5:2:1",
      "brand" : "EMULEX",
      "model" : "LPe12004",
      "rev" : "03",
      "firmware" : "2.10.X.3",
      "serial" : "5CF20502GX"
    }, {
      "nsp" : "1:6:1",
      "brand" : "EMULEX",
      "model" : "LPe12004",
      "rev" : "03",
      "firmware" : "2.10.X.3",
      "serial" : "THT35275MN"
    }, {
      "nsp" : "5:2:2",
      "brand" : "EMULEX",
      "model" : "LPe12004",
      "rev" : "03",
      "firmware" : "2.10.X.3",
      "serial" : "5CF20502GX"
    }, {
      "nsp" : "1:7:1",
      "brand" : "QLOGIC",
      "model" : "QLE8242",
      "rev" : "58",
      "firmware" : "4.15.27",
      "serial" : "PCGLT0AST2VE47"
    }, {
      "nsp" : "0:0:4",
      "brand" : "EMULEX",
      "model" : "LPe12004",
      "rev" : "03",
      "firmware" : "2.10.X.3",
      "serial" : "5CF15005C3"
    }, {
      "nsp" : "4:2:3",
      "brand" : "EMULEX",
      "model" : "LPe12004",
      "rev" : "03",
      "firmware" : "2.10.X.3",
      "serial" : "THC1294WPY"
    }, {
      "nsp" : "0:6:2",
      "brand" : "EMULEX",
      "model" : "LPe12004",
      "rev" : "03",
      "firmware" : "2.10.X.3",
      "serial" : "5CF14700VS"
    }, {
      "nsp" : "4:6:4",
      "brand" : "EMULEX",
      "model" : "LPe12004",
      "rev" : "03",
      "firmware" : "2.10.X.3",
      "serial" : "5CF1460272"
    }, {
      "nsp" : "1:6:4",
      "brand" : "EMULEX",
      "model" : "LPe12004",
      "rev" : "03",
      "firmware" : "2.10.X.3",
      "serial" : "THT35275MN"
    }, {
      "nsp" : "4:5:4",
      "brand" : "EMULEX",
      "model" : "LPe12004",
      "rev" : "03",
      "firmware" : "2.10.X.3",
      "serial" : "5CF229030V"
    }, {
      "nsp" : "0:2:3",
      "brand" : "EMULEX",
      "model" : "LPe12004",
      "rev" : "03",
      "firmware" : "2.10.X.3",
      "serial" : "THC1244KGN"
    }, {
      "nsp" : "0:5:4",
      "brand" : "EMULEX",
      "model" : "LPe12004",
      "rev" : "03",
      "firmware" : "2.10.X.3",
      "serial" : "5CF231001Y"
    }, {
      "nsp" : "0:4:1",
      "brand" : "EMULEX",
      "model" : "LPe12004",
      "rev" : "03",
      "firmware" : "2.10.X.3",
      "serial" : "THC1294TZR"
    }, {
      "nsp" : "5:6:2",
      "brand" : "EMULEX",
      "model" : "LPe12004",
      "rev" : "03",
      "firmware" : "2.10.X.3",
      "serial" : "THC12510SW"
    }, {
      "nsp" : "4:6:1",
      "brand" : "EMULEX",
      "model" : "LPe12004",
      "rev" : "03",
      "firmware" : "2.10.X.3",
      "serial" : "5CF1460272"
    }, {
      "nsp" : "4:0:1",
      "brand" : "EMULEX",
      "model" : "LPe12004",
      "rev" : "03",
      "firmware" : "2.10.X.3",
      "serial" : "5CF2290343"
    }, {
      "nsp" : "5:7:2",
      "brand" : "QLOGIC",
      "model" : "QLE8242",
      "rev" : "58",
      "firmware" : "4.15.27",
      "serial" : "PCGLT0AST2JD2U"
    }, {
      "nsp" : "4:1:2",
      "brand" : "EMULEX",
      "model" : "LPe12004",
      "rev" : "03",
      "firmware" : "2.10.X.3",
      "serial" : "5CF2300036"
    } ]
  },
  "capacity" : {
    "total" : {
      "virtualSizeTiB" : 27.1953125,
      "sizeTiB" : 144.634765625,
      "freeTiB" : 116.1982421875,
      "freePct" : 80.33908081054688,
      "allocatedCapacityTiB" : 24.376953125,
      "failedCapacityTiB" : 4.0595703125,
      "systemAllocatedTiB" : 9.2099609375,
      "volumesAllocatedTiB" : 15.1669921875,
      "otherAllocatedTiB" : 0,
      "volumesVirtualSizeTiB" : 27.1953125,
      "usedSpaceTiB" : 7.194091796875,
      "compactionRatio" : 4.03000020980835,
      "overprovisioningRatio" : 0.28999999165534973
    },
    "byType" : {
      "fc" : {
        "sizeTiB" : 30.376953125,
        "freeTiB" : 17.2548828125,
        "freePct" : 56.802547454833984,
        "usedBalancedPct" : 99.15031433105469,
        "sizeBalancedPct" : 100
      },
      "nl" : {
        "sizeTiB" : 112.8125,
        "freeTiB" : 97.498046875,
        "freePct" : 86.42486572265625,
        "usedBalancedPct" : 99.92350769042969,
        "sizeBalancedPct" : 100
      },
      "ssd" : {
        "sizeTiB" : 1.4453125,
        "freeTiB" : 1.4453125,
        "freePct" : 100,
        "sizeBalancedPct" : 100
      }
    },
    "arrayType" : "MixedArray"
  },
  "performance" : {
    "portBandwidthData" : {
      "total" : {
        "dataRateKBPSAvg" : 273,
        "dataRateKBPSMax" : 342,
        "dataRateKBPSMin" : 207,
        "iopsAvg" : 33,
        "iopsMax" : 34,
        "iopsMin" : 31,
        "ioSizeAvg" : 5.2445454597473145,
        "ioSizeMax" : 85,
        "ioSizeMin" : 0,
        "queueLengthAvg" : 0,
        "queueLengthMax" : 0,
        "queueLengthMin" : 0,
        "serviceTimeMSAvg" : 0.8290908932685852,
        "serviceTimeMSMax" : 5,
        "serviceTimeMSMin" : 0
      },
      "read" : {
        "dataRateKBPSAvg" : 96,
        "dataRateKBPSMax" : 157,
        "dataRateKBPSMin" : 35,
        "iopsAvg" : 11,
        "iopsMax" : 11,
        "iopsMin" : 11,
        "ioSizeAvg" : 2.5609090328216553,
        "ioSizeMax" : 91,
        "ioSizeMin" : 0,
        "queueLengthAvg" : 0,
        "queueLengthMax" : 0,
        "queueLengthMin" : 0,
        "serviceTimeMSAvg" : 1.6836363077163696,
        "serviceTimeMSMax" : 5,
        "serviceTimeMSMin" : 0
      },
      "write" : {
        "dataRateKBPSAvg" : 179,
        "dataRateKBPSMax" : 186,
        "dataRateKBPSMin" : 172,
        "iopsAvg" : 22,
        "iopsMax" : 22,
        "iopsMin" : 20,
        "ioSizeAvg" : 4.506363868713379,
        "ioSizeMax" : 10,
        "ioSizeMin" : 0,
        "queueLengthAvg" : 0,
        "queueLengthMax" : 0,
        "queueLengthMin" : 0,
        "serviceTimeMSAvg" : 0,
        "serviceTimeMSMax" : 0,
        "serviceTimeMSMin" : 0
      }
    },
    "summary" : {
      "portInfo" : {
        "readServiceTimeColMillis" : 1.6836363077163696,
        "writeServiceTimeColMillis" : 0,
        "totalServiceTimeColMillis" : 0.8290908932685852
      }
    }
  },
  "disks" : {
    "total" : {
      "diskCount" : 137,
      "diskCountNormal" : 134,
      "diskCountFailed" : 3
    },
    "byType" : {
      "fc" : {
        "diskCount" : 65,
        "diskCountBalancedPct" : 100,
        "diskCountNormal" : 64,
        "diskCountFailed" : 1,
        "state" : "failed"
      },
      "nl" : {
        "diskCount" : 64,
        "diskCountBalancedPct" : 100,
        "diskCountNormal" : 62,
        "diskCountFailed" : 2,
        "state" : "failed"
      },
      "ssd" : {
        "diskCount" : 8,
        "diskCountBalancedPct" : 100,
        "diskCountNormal" : 8,
        "state" : "normal"
      }
    },
    "state" : "failed"
  },
  "nodes" : {
    "nodeCount" : 4,
    "nodeCountOffline" : 0,
    "nodeCountMissing" : 0,
    "nodeTimeSkewSecs" : 0,
    "cageCount" : 8,
    "cpuAvgMax" : 2,
    "cpuMedianMax" : 2
  },
  "updated" : "2018-05-10T16:58:13Z",
  "authorized" : {
    "tenants" : [ "1045027157", "hpe" ]
  },
  "date" : "2018-05-10T16:58:13Z"
}