{
  "serialNumberInserv" : "8888877",
  "system" : {
    "companyName" : "Talia Josephine Wagner",
    "model" : "7200c",
    "fullModel" : "HPE_3PAR 7200c",
    "osVersion" : "3.3.1.410 (MU2)",
    "patches" : [ ],
    "sp" : {
      "spId" : "6709918",
      "spModel" : "VMware Virtual Platform",
      "spVersion" : "5.0.3.1-25112",
      "spPatches" : [ "1" ]
    },
    "productSKU" : "E7X67A",
    "productFamily" : "7000",
    "recommended" : {
      "criticalPatches" : [ "P30" ],
      "conditionalPatches" : [ "P32" ]
    },
    "portsHWInfo" : [ {
      "nsp" : "0:0:1",
      "brand" : "LSI",
      "model" : "9205-8e",
      "rev" : "01",
      "firmware" : "17.11.03.00",
      "serial" : "Onboard"
    }, {
      "nsp" : "0:1:1",
      "brand" : "EMULEX",
      "model" : "LPe12002",
      "rev" : "03",
      "firmware" : "2.10.X.3",
      "serial" : "Onboard"
    }, {
      "nsp" : "0:0:2",
      "brand" : "LSI",
      "model" : "9205-8e",
      "rev" : "01",
      "firmware" : "17.11.03.00",
      "serial" : "Onboard"
    }, {
      "nsp" : "0:1:2",
      "brand" : "EMULEX",
      "model" : "LPe12002",
      "rev" : "03",
      "firmware" : "2.10.X.3",
      "serial" : "Onboard"
    }, {
      "nsp" : "1:1:1",
      "brand" : "EMULEX",
      "model" : "LPe12002",
      "rev" : "03",
      "firmware" : "2.10.X.3",
      "serial" : "Onboard"
    }, {
      "nsp" : "1:0:1",
      "brand" : "LSI",
      "model" : "9205-8e",
      "rev" : "01",
      "firmware" : "17.11.03.00",
      "serial" : "Onboard"
    }, {
      "nsp" : "1:1:2",
      "brand" : "EMULEX",
      "model" : "LPe12002",
      "rev" : "03",
      "firmware" : "2.10.X.3",
      "serial" : "Onboard"
    }, {
      "nsp" : "1:3:1",
      "brand" : "Intel",
      "model" : "e1000e",
      "firmware" : "3.2.6-k",
      "serial" : "Onboard"
    }, {
      "nsp" : "1:0:2",
      "brand" : "LSI",
      "model" : "9205-8e",
      "rev" : "01",
      "firmware" : "17.11.03.00",
      "serial" : "Onboard"
    }, {
      "nsp" : "0:3:1",
      "brand" : "Intel",
      "model" : "e1000e",
      "firmware" : "3.2.6-k",
      "serial" : "Onboard"
    } ]
  },
  "capacity" : {
    "total" : {
      "virtualSizeTiB" : 10.568359375,
      "sizeTiB" : 19.1796875,
      "freeTiB" : 6.0439453125,
      "freePct" : 31.512218475341797,
      "allocatedCapacityTiB" : 13.1357421875,
      "failedCapacityTiB" : 0,
      "systemAllocatedTiB" : 2.4482421875,
      "volumesAllocatedTiB" : 10.6875,
      "otherAllocatedTiB" : 0,
      "volumesVirtualSizeTiB" : 10.568359375,
      "usedSpaceTiB" : 7.71044921875,
      "compactionRatio" : 1.3700000047683716,
      "overprovisioningRatio" : 0.8199999928474426
    },
    "byType" : {
      "fc" : {
        "sizeTiB" : 17.4375,
        "freeTiB" : 5.3017578125,
        "freePct" : 30.404346466064453,
        "usedBalancedPct" : 100,
        "sizeBalancedPct" : 100
      },
      "ssd" : {
        "sizeTiB" : 1.7421875,
        "freeTiB" : 0.7421875,
        "freePct" : 42.60089874267578,
        "usedBalancedPct" : 100,
        "sizeBalancedPct" : 100
      }
    },
    "arrayType" : "MixedArray"
  },
  "performance" : {
    "portBandwidthData" : {
      "total" : {
        "dataRateKBPSAvg" : 13408,
        "dataRateKBPSMax" : 29536,
        "dataRateKBPSMin" : 7232,
        "iopsAvg" : 903,
        "iopsMax" : 1336,
        "iopsMin" : 726,
        "ioSizeAvg" : 12.351218223571777,
        "ioSizeMax" : 51,
        "ioSizeMin" : 8,
        "queueLengthAvg" : 0,
        "queueLengthMax" : 0.5,
        "queueLengthMin" : 0,
        "serviceTimeMSAvg" : 0.5337984561920166,
        "serviceTimeMSMax" : 3,
        "serviceTimeMSMin" : 0
      },
      "read" : {
        "dataRateKBPSAvg" : 2731,
        "dataRateKBPSMax" : 10425,
        "dataRateKBPSMin" : 68,
        "iopsAvg" : 92,
        "iopsMax" : 328,
        "iopsMin" : 7,
        "ioSizeAvg" : 16.364347457885742,
        "ioSizeMax" : 84,
        "ioSizeMin" : 3,
        "queueLengthAvg" : 0,
        "queueLengthMax" : 0,
        "queueLengthMin" : 0,
        "serviceTimeMSAvg" : 3.1852173805236816,
        "serviceTimeMSMax" : 10,
        "serviceTimeMSMin" : 0
      },
      "write" : {
        "dataRateKBPSAvg" : 10678,
        "dataRateKBPSMax" : 19111,
        "dataRateKBPSMin" : 7158,
        "iopsAvg" : 811,
        "iopsMax" : 1010,
        "iopsMin" : 717,
        "ioSizeAvg" : 11.766313552856445,
        "ioSizeMax" : 39,
        "ioSizeMin" : 8,
        "queueLengthAvg" : 0,
        "queueLengthMax" : 0,
        "queueLengthMin" : 0,
        "serviceTimeMSAvg" : 0.008088779635727406,
        "serviceTimeMSMax" : 1,
        "serviceTimeMSMin" : 0
      }
    },
    "summary" : {
      "portInfo" : {
        "readServiceTimeColMillis" : 3.1852173805236816,
        "writeServiceTimeColMillis" : 0.008088779635727406,
        "totalServiceTimeColMillis" : 0.5337984561920166
      }
    }
  },
  "disks" : {
    "total" : {
      "diskCount" : 20,
      "diskCountNormal" : 20
    },
    "byType" : {
      "fc" : {
        "diskCount" : 16,
        "diskCountBalancedPct" : 100,
        "diskCountNormal" : 16,
        "state" : "normal"
      },
      "ssd" : {
        "diskCount" : 4,
        "diskCountBalancedPct" : 100,
        "diskCountNormal" : 4,
        "state" : "normal"
      }
    },
    "state" : "normal"
  },
  "nodes" : {
    "nodeCount" : 2,
    "nodeCountOffline" : 0,
    "nodeCountMissing" : 0,
    "nodeTimeSkewSecs" : 0,
    "cageCount" : 1,
    "cpuAvgMax" : 2,
    "cpuMedianMax" : 2
  },
  "updated" : "2018-09-09T12:29:17Z",
  "authorized" : {
    "tenants" : [ "hpe" ]
  },
  "date" : "2018-09-09T12:29:17Z"
}